{"houses":[{"id":"h1776221326265","name":"绿地滨江汇 1015","area":"38","floor":"10","distance":"çµé©´ 10min","type":"","rent":"2000","utility":"","elecPrice":"0.73","waterPrice":"5.8","waterUsage":"2","elecUsage":"425","serviceFee":"0","propFee":"3.45","deposit":"","agentFee":"åä¸ªææ¿ç§","total":"2550","decor":"","elevator":"","direction":"","appliance":"ç©ºè°ãæ´è¡£æºãç­æ°´å¨ãå°ç®±","score":"7","contact":"èµå°å¹³","visitDate":"4æ14æ¥  20:00","pros":"æ¬å®¶è·ç¦»è¿","cons":"æ¿é´ä¸æ¯å¾å¤§ï¼æç¹è","note":"","updatedAt":"2026/4/15 13:48:13"}],"checks":[false,false,false,false,false,false,false,false,false,false,false,false,false,false,false,false,false,false,false,false,false],"updatedAt":"2026-04-15T05:48:13.284Z"}